parsefire/__init__.py
parsefire/parser.py
parsefire-2024.9.1.dist-info/LICENSE
parsefire-2024.9.1.dist-info/METADATA
parsefire-2024.9.1.dist-info/WHEEL
parsefire-2024.9.1.dist-info/RECORD
