Metadata-Version: 2.1
Name: parsefire
Version: 2024.9.1
Summary: Python Package for consistent data mining from unstructured text documents.
License: MIT
Author: Michel Fodje
Author-email: michel4j@gmail.com
Requires-Python: >=3.9,<4.0
Classifier: License :: OSI Approved :: MIT License
Classifier: Programming Language :: Python :: 3
Classifier: Programming Language :: Python :: 3.9
Classifier: Programming Language :: Python :: 3.10
Classifier: Programming Language :: Python :: 3.11
Classifier: Programming Language :: Python :: 3.12
Requires-Dist: PyYAML (>=6.0.0,<7.0.0)
